dbsync/__init__.py
dbsync/config.py
dbsync/cli/README.md
dbsync/cli/__init__.py
dbsync/cli/__main__.py
dbsync/cli/benchmark.py
dbsync/cli/coverage.py
dbsync/cli/info.py
dbsync/cli/main.py
dbsync/cli/performance.py
dbsync/cli/query.py
dbsync/cli/query_new.py
dbsync/cli/validate.py
dbsync/examples/__init__.py
dbsync/examples/queries/__init__.py
dbsync/examples/queries/chain_metadata.py
dbsync/examples/queries/governance.py
dbsync/examples/queries/multi_asset.py
dbsync/examples/queries/pool_management.py
dbsync/examples/queries/smart_contracts.py
dbsync/examples/queries/staking_delegation.py
dbsync/examples/queries/transaction_analysis.py
dbsync/models/__init__.py
dbsync/models/assets.py
dbsync/models/base.py
dbsync/models/blockchain.py
dbsync/models/foundation.py
dbsync/models/governance.py
dbsync/models/pools.py
dbsync/models/protocol.py
dbsync/models/scripts.py
dbsync/models/staking.py
dbsync/models/transactions.py
dbsync/models/treasury.py
dbsync/session/__init__.py
dbsync/session/async_.py
dbsync/session/sync.py
dbsync/session/unified.py
dbsync/utils/__init__.py
dbsync/utils/connection_test.py
dbsync/utils/types.py
dbsync_py-1.1.2.dist-info/METADATA
dbsync_py-1.1.2.dist-info/WHEEL
dbsync_py-1.1.2.dist-info/entry_points.txt
dbsync_py-1.1.2.dist-info/licenses/LICENSE
dbsync_py-1.1.2.dist-info/RECORD
