Metadata-Version: 2.4
Name: dbsync-py
Version: 1.1.2
Summary: Python helper package for interacting with Cardano DB Sync databases
Project-URL: Homepage, https://github.com/TheElderMillenial/dbsync-py
Project-URL: Bug Reports, https://github.com/TheElderMillenial/dbsync-py/issues
Project-URL: Source, https://github.com/TheElderMillenial/dbsync-py
Project-URL: Documentation, https://TheElderMillenial.github.io/dbsync-py/
Author-email: TheElderMillenial <eldermillenial@protonmail.com>
License: Apache-2.0
License-File: LICENSE
Keywords: blockchain,cardano,database,orm,postgresql,sqlalchemy
Classifier: Development Status :: 3 - Alpha
Classifier: Intended Audience :: Developers
Classifier: License :: OSI Approved :: Apache Software License
Classifier: Programming Language :: Python :: 3
Classifier: Programming Language :: Python :: 3.12
Classifier: Programming Language :: Python :: 3.13
Classifier: Topic :: Database :: Database Engines/Servers
Classifier: Topic :: Software Development :: Libraries :: Python Modules
Requires-Python: >=3.12
Requires-Dist: click>=8.2.1
Requires-Dist: psycopg[binary,pool]>=3.1.0
Requires-Dist: pycardano>=0.10.0
Requires-Dist: python-dotenv>=1.0.0
Requires-Dist: sqlmodel>=0.0.14
Provides-Extra: async
Requires-Dist: asyncpg>=0.28.0; extra == 'async'
Requires-Dist: greenlet>=2.0.0; extra == 'async'
Provides-Extra: dev
Requires-Dist: bandit>=1.7.0; extra == 'dev'
Requires-Dist: build>=0.10.0; extra == 'dev'
Requires-Dist: bump-my-version>=1.2.0; extra == 'dev'
Requires-Dist: coverage[toml]>=7.0.0; extra == 'dev'
Requires-Dist: hypothesis>=6.135.20; extra == 'dev'
Requires-Dist: matplotlib>=3.8.0; extra == 'dev'
Requires-Dist: memory-profiler>=0.61.0; extra == 'dev'
Requires-Dist: mypy>=1.5.0; extra == 'dev'
Requires-Dist: pandas>=2.1.0; extra == 'dev'
Requires-Dist: pre-commit>=3.0.0; extra == 'dev'
Requires-Dist: psutil>=7.0.0; extra == 'dev'
Requires-Dist: pytest-asyncio>=0.21.0; extra == 'dev'
Requires-Dist: pytest-benchmark>=5.1.0; extra == 'dev'
Requires-Dist: pytest-cov>=4.0.0; extra == 'dev'
Requires-Dist: pytest-xdist>=3.0.0; extra == 'dev'
Requires-Dist: pytest>=7.0.0; extra == 'dev'
Requires-Dist: requests>=2.32.4; extra == 'dev'
Requires-Dist: ruff>=0.0.280; extra == 'dev'
Requires-Dist: setuptools>=80.9.0; extra == 'dev'
Provides-Extra: docs
Requires-Dist: mkdocs-gen-files>=0.5.0; extra == 'docs'
Requires-Dist: mkdocs-material>=9.0.0; extra == 'docs'
Requires-Dist: mkdocstrings[python]>=0.22.0; extra == 'docs'
Requires-Dist: pymdown-extensions>=10.0.0; extra == 'docs'
